{
  "title": "[GẤP] KỸ SƯ IT LẬP TRÌNH WEB - NHÀ MÁY 1",
  "description": "Mô tả công việc: Vui lòng truy cập link https://www.careerlink.vn/tim-viec-lam/gap-ky-su-it-lap-trinh-web-nha-may-1/2919280?source=site để biết thêm chi tiết.",
  "location": "Hồ Chí Minh",
  "experience": "Chưa xác định",
  "requirement": "Chưa xác định",
  "salary": "Thương lượng",
  "expiration_date": "2024-09-16",
  "job_type": "Nhân viên",
  "created_at": "2024-09-17",
  "url": "https://www.careerlink.vn/tim-viec-lam/gap-ky-su-it-lap-trinh-web-nha-may-1/2919280?source=site",
  "company": "SAIGON PRECISION COMPANY LTD. (Misumi Group Inc)"
}